<?xml version="1.0" encoding="UTF-8" standalone="no"?>
<!--
  Unpublished Work © 2012 Detica Solutions Limited (Ireland). All rights Reserved.
-->
<rffilespec comments="filespec_CUSTOMER_TYPE.xml" name="filespec_CUSTOMER_TYPE.xml">
	<lineskip-begin>0</lineskip-begin>
	<lineskip-end>0</lineskip-end>
	<lineskip-empty>1</lineskip-empty>
        <file-encoding>UTF-8</file-encoding>
	<rfrecordspec datatype="TEXT" fieldDelimiter="|" fieldname="ProductId" fixedlength="false"/>
	<rfrecordspec datatype="TEXT" fieldDelimiter="|" fieldname="ProductName" fixedlength="false"/>
	<rfrecordspec datatype="TEXT" fieldDelimiter="|" fieldname="ProductGroup" fixedlength="false"/>
	<rfrecordspec datatype="TEXT" fieldDelimiter="|" fieldname="ProductClass" fixedlength="false"/>
	<rfrecordspec datatype="TEXT" fieldDelimiter="" fieldname="ProductLine" fixedlength="false"/>
</rffilespec>
